mypkg/__init__.py
mypkg/states_info.py
mypkg/subpackage/__init__.py
mypkg_nikita-0.0.4.dist-info/METADATA
mypkg_nikita-0.0.4.dist-info/WHEEL
mypkg_nikita-0.0.4.dist-info/top_level.txt
mypkg_nikita-0.0.4.dist-info/RECORD
